{"BaseModel.a4f563eb-cd83-405c-bcc3-9f75601d0e91": {"id": "a4f563eb-cd83-405c-bcc3-9f75601d0e91", "created_at": "2024-06-16T20:31:00.162220", "updated_at": "2024-06-16T20:31:00.162239", "name": "My_First_Model", "my_number": 89, "__class__": "BaseModel"}, "BaseModel.922a6fcd-1cf7-4786-8488-707df3605704": {"id": "922a6fcd-1cf7-4786-8488-707df3605704", "created_at": "2024-06-16T20:31:02.207548", "updated_at": "2024-06-16T20:31:02.207560", "name": "My_First_Model", "my_number": 89, "__class__": "BaseModel"}, "BaseModel.0ceedc37-759a-4206-83d3-080c12c54b57": {"id": "0ceedc37-759a-4206-83d3-080c12c54b57", "created_at": "2024-06-16T20:44:03.894764", "updated_at": "2024-06-16T20:44:03.894824", "name": "My_First_Model", "my_number": 89, "__class__": "BaseModel"}, "BaseModel.afa3f435-3592-4556-baff-4d500973b923": {"id": "afa3f435-3592-4556-baff-4d500973b923", "created_at": "2024-06-16T20:44:05.818333", "updated_at": "2024-06-16T20:44:05.818346", "name": "My_First_Model", "my_number": 89, "__class__": "BaseModel"}, "BaseModel.bfcc9a69-92f1-4b65-8e62-61234d03c078": {"id": "bfcc9a69-92f1-4b65-8e62-61234d03c078", "created_at": "2025-06-10T19:19:37.800178", "updated_at": "2025-06-10T19:19:37.839896", "__class__": "BaseModel"}, "BaseModel.eaa4744a-08a7-432b-aa54-e30a57b4aaf6": {"id": "eaa4744a-08a7-432b-aa54-e30a57b4aaf6", "created_at": "2025-06-10T19:32:25.419134", "updated_at": "2025-06-10T19:32:25.419176", "__class__": "BaseModel"}}